snooty/__init__.py
snooty/__main__.py
snooty/cache.py
snooty/config.toml
snooty/diagnostics.py
snooty/eventparser.py
snooty/flutter.py
snooty/intersphinx.py
snooty/language_server.py
snooty/lsp.py
snooty/main.py
snooty/n.py
snooty/openapi.py
snooty/page.py
snooty/parser.py
snooty/performance_report.py
snooty/postprocess.py
snooty/rstparser.py
snooty/rstspec-consolidated.toml
snooty/rstspec.toml
snooty/specparser.py
snooty/target_database.py
snooty/test_devhub.py
snooty/test_diagnostic.py
snooty/test_intersphinx.py
snooty/test_language_server.py
snooty/test_main.py
snooty/test_mongodb_domain.py
snooty/test_openapi.py
snooty/test_parser.py
snooty/test_postprocess.py
snooty/test_postprocess_old_and_monolithic.py
snooty/test_project.py
snooty/test_sharedinclude.py
snooty/test_specparser.py
snooty/test_types.py
snooty/test_util.py
snooty/types.py
snooty/util.py
snooty/util_test.py
snooty/builders/__init__.py
snooty/builders/man.py
snooty/builders/test_man.py
snooty/gizaparser/__init__.py
snooty/gizaparser/apiargs.py
snooty/gizaparser/extracts.py
snooty/gizaparser/nodes.py
snooty/gizaparser/options.py
snooty/gizaparser/parse.py
snooty/gizaparser/published_branches.py
snooty/gizaparser/release.py
snooty/gizaparser/steps.py
snooty/gizaparser/test_extracts.py
snooty/gizaparser/test_nodes.py
snooty/gizaparser/test_parse.py
snooty/gizaparser/test_release.py
snooty/gizaparser/test_steps.py
snooty_lextudio-1.12.0.dist-info/entry_points.txt
snooty_lextudio-1.12.0.dist-info/LICENSE
snooty_lextudio-1.12.0.dist-info/LICENSE.openssl
snooty_lextudio-1.12.0.dist-info/LICENSE.python
snooty_lextudio-1.12.0.dist-info/WHEEL
snooty_lextudio-1.12.0.dist-info/METADATA
snooty_lextudio-1.12.0.dist-info/RECORD
