Metadata-Version: 1.1
Name: snooty-lextudio
Version: 1.12.0
Summary: The Snooty documentation writer's tool.
Home-page: https://github.com/vscode-restructuredtext/snooty-parser
Author: MongoDB, inc.
Author-email: i80and@foxquill.com
